AUTHORS
CHANGELOG.rst
LICENSE
MANIFEST.in
README
README.rst
requirements.txt
setup.cfg
setup.py
docs/CHANGELOG.rst
docs/CONTRIBUTING.rst
docs/LICENSE.rst
docs/README.rst
docs/conf.py
docs/index.rst
docs/html/index.html
rebookmaker/__init__.py
rebookmaker/rebookmaker
rebookmaker/template.py
rebookmaker.egg-info/PKG-INFO
rebookmaker.egg-info/SOURCES.txt
rebookmaker.egg-info/dependency_links.txt
rebookmaker.egg-info/not-zip-safe
rebookmaker.egg-info/requires.txt
rebookmaker.egg-info/top_level.txt
rebookmaker/data/templates/container.xml.jinja
rebookmaker/data/templates/content.opf.jinja
rebookmaker/data/templates/cover.html.jinja
rebookmaker/data/templates/nav.html.jinja
rebookmaker/data/templates/onepixel.png
rebookmaker/data/templates/onepixel.xcf
rebookmaker/data/templates/toc.html.jinja
rebookmaker/data/templates/toc.ncx.jinja
tests/__init__.py
tests/test_rebook.py
tests/test_sanity.py