Metadata-Version: 2.1
Name: rebookmaker
Version: 0.8.11
Summary: EPUB generator
Home-page: https://github.com/shlomif/rebookmaker
Author: Shlomi Fish
Author-email: shlomif@cpan.org
License: 3-clause BSD
Keywords: rebookmaker
Platform: any
Classifier: Development Status :: 1 - Planning
Classifier: Programming Language :: Python
Classifier: Programming Language :: Python :: 3
Classifier: Programming Language :: Python :: 3.6
Classifier: Programming Language :: Python :: 3.7
Classifier: Programming Language :: Python :: 3.8
Classifier: Programming Language :: Python :: 3.9
Classifier: Programming Language :: Python :: 3.10
Classifier: Programming Language :: Python :: 3.11
License-File: LICENSE
License-File: AUTHORS
